cpf_alfacnpj/__init__.py
cpf_alfacnpj/cnpj.py
cpf_alfacnpj/cpf.py
tests/__init__.py
tests/test_validar_cnpj.py
tests/test_validar_cnpj_alfanumerico.py
tests/test_validar_cpf.py
cpf_alfacnpj-0.3.0.dist-info/LICENSE
cpf_alfacnpj-0.3.0.dist-info/METADATA
cpf_alfacnpj-0.3.0.dist-info/WHEEL
cpf_alfacnpj-0.3.0.dist-info/entry_points.txt
cpf_alfacnpj-0.3.0.dist-info/top_level.txt
cpf_alfacnpj-0.3.0.dist-info/RECORD
