Metadata-Version: 2.1
Name: cpf_alfacnpj
Version: 0.3.0
Summary: Biblioteca de validação de CPF e CNPJ, inclusive com suporte ao CNPJ alfanumérico (2026)
Home-page: https://github.com/andreydani/cpf_cnpj
Author: Andrey Sant'Anna
Author-email: andreysantanna@gmail.com
Classifier: Programming Language :: Python :: 3
Classifier: License :: OSI Approved :: MIT License
Classifier: Operating System :: OS Independent
Requires-Python: >=3.6
License-File: LICENSE
